aws_ops_alpha/__init__.py
aws_ops_alpha/_version.py
aws_ops_alpha/api.py
aws_ops_alpha/constants.py
aws_ops_alpha/env_var.py
aws_ops_alpha/logger.py
aws_ops_alpha/paths.py
aws_ops_alpha/rule_set.py
aws_ops_alpha/aws_helpers/__init__.py
aws_ops_alpha/aws_helpers/_build_layer_in_container.py
aws_ops_alpha/aws_helpers/api.py
aws_ops_alpha/aws_helpers/aws_cdk_helpers.py
aws_ops_alpha/aws_helpers/aws_chalice_helpers.py
aws_ops_alpha/aws_helpers/aws_ecr_helpers.py
aws_ops_alpha/aws_helpers/aws_glue_helpers.py
aws_ops_alpha/aws_helpers/aws_lambda_helpers.py
aws_ops_alpha/aws_helpers/aws_sfn_helpers.py
aws_ops_alpha/aws_helpers/python_helpers.py
aws_ops_alpha/aws_helpers/rich_helpers.py
aws_ops_alpha/boostrap/__init__.py
aws_ops_alpha/boostrap/api.py
aws_ops_alpha/boostrap/helpers.py
aws_ops_alpha/boostrap/aws_codepipeline/__init__.py
aws_ops_alpha/boostrap/aws_codepipeline/api.py
aws_ops_alpha/boostrap/aws_codepipeline/task.py
aws_ops_alpha/boostrap/github_action/__init__.py
aws_ops_alpha/boostrap/github_action/api.py
aws_ops_alpha/boostrap/github_action/task.py
aws_ops_alpha/boostrap/multi_account/__init__.py
aws_ops_alpha/boostrap/multi_account/api.py
aws_ops_alpha/boostrap/multi_account/task.py
aws_ops_alpha/boto_ses/__init__.py
aws_ops_alpha/boto_ses/api.py
aws_ops_alpha/boto_ses/impl.py
aws_ops_alpha/config/__init__.py
aws_ops_alpha/config/api.py
aws_ops_alpha/config/app.py
aws_ops_alpha/config/deploy.py
aws_ops_alpha/config/main.py
aws_ops_alpha/config/name.py
aws_ops_alpha/docs/__init__.py
aws_ops_alpha/git/__init__.py
aws_ops_alpha/git/api.py
aws_ops_alpha/git/impl.py
aws_ops_alpha/multi_env/__init__.py
aws_ops_alpha/multi_env/api.py
aws_ops_alpha/multi_env/impl.py
aws_ops_alpha/project/__init__.py
aws_ops_alpha/project/api.py
aws_ops_alpha/project/simple_cdk/__init__.py
aws_ops_alpha/project/simple_cdk/api.py
aws_ops_alpha/project/simple_cdk/gen_code.py
aws_ops_alpha/project/simple_cdk/rule_set.py
aws_ops_alpha/project/simple_cdk/should_we_do_it.tsv
aws_ops_alpha-0.2.1.dist-info/AUTHORS.rst
aws_ops_alpha-0.2.1.dist-info/LICENSE.txt
aws_ops_alpha-0.2.1.dist-info/METADATA
aws_ops_alpha-0.2.1.dist-info/WHEEL
aws_ops_alpha-0.2.1.dist-info/top_level.txt
aws_ops_alpha-0.2.1.dist-info/RECORD
