Metadata-Version: 2.1
Name: aws_ops_alpha
Version: 0.2.1
Summary: A devops best practices for AWS projects. Designed for production-ready, multi-environments deployment projects
Home-page: https://github.com/MacHu-GWU/aws_ops_alpha-project
Download-URL: https://pypi.python.org/pypi/aws_ops_alpha/0.2.1#downloads
Author: Sanhe Hu
Author-email: husanhe@gmail.com
Maintainer: Sanhe Hu
Maintainer-email: husanhe@gmail.com
License: MIT
Platform: Windows
Platform: MacOS
Platform: Unix
Classifier: Development Status :: 4 - Beta
Classifier: Intended Audience :: Developers
Classifier: License :: OSI Approved :: GNU General Public License (GPL)
Classifier: Natural Language :: English
Classifier: Operating System :: Microsoft :: Windows
Classifier: Operating System :: MacOS
Classifier: Operating System :: Unix
Classifier: Programming Language :: Python
Classifier: Programming Language :: Python :: 3.8
Classifier: Programming Language :: Python :: 3.9
Classifier: Programming Language :: Python :: 3.10
Classifier: Programming Language :: Python :: 3.11
Classifier: Programming Language :: Python :: 3.12
Classifier: Programming Language :: Python :: 3 :: Only
Requires-Python: >=3.8
License-File: LICENSE.txt
License-File: AUTHORS.rst
Requires-Dist: boto-session-manager <2.0.0,>=1.7.2
Requires-Dist: s3pathlib <3.0.0,>=2.1.2
Requires-Dist: pyproject-ops <1.0.0,>=0.8.1
Requires-Dist: aws-console-url <2.0.0,>=1.4.1
Requires-Dist: aws-lambda-layer <1.0.0,>=0.5.1
Requires-Dist: aws-glue-artifact <1.0.0,>=0.2.1
Requires-Dist: tt4human <1.0.0,>=0.3.1
Requires-Dist: config-patterns <2.0.0,>=1.0.6
Requires-Dist: config-patterns[aws]
Provides-Extra: docs
Requires-Dist: Sphinx ==5.3.0 ; extra == 'docs'
Requires-Dist: sphinx-jinja ==2.0.2 ; extra == 'docs'
Requires-Dist: sphinx-copybutton ==0.5.1 ; extra == 'docs'
Requires-Dist: sphinx-design ==0.5.0 ; extra == 'docs'
Requires-Dist: furo ==2023.03.27 ; extra == 'docs'
Requires-Dist: nbsphinx ==0.8.12 ; extra == 'docs'
Requires-Dist: rstobj ==1.2.1 ; extra == 'docs'
Requires-Dist: pygments ==2.15.1 ; extra == 'docs'
Requires-Dist: ipython ==8.10.0 ; extra == 'docs'
Requires-Dist: docfly ==2.0.3 ; extra == 'docs'
Provides-Extra: tests
Requires-Dist: pytest ; extra == 'tests'
Requires-Dist: pytest-cov ; extra == 'tests'
Requires-Dist: jinja2 ; extra == 'tests'
Requires-Dist: rich ; extra == 'tests'
